{"__symbolic":"module","version":4,"exports":[{"from":"./lib/yes-or-no/yes-or-no.component"},{"from":"./lib/yes-or-no.module"},{"from":"./lib/yes-or-no.service"},{"from":"./lib/models"}],"metadata":{"DesignSystemInitiafyModule":{"__symbolic":"class","decorators":[{"__symbolic":"call","expression":{"__symbolic":"reference","module":"@angular/core","name":"NgModule","line":30,"character":1},"arguments":[{"imports":[{"__symbolic":"reference","module":"@angular/common","name":"CommonModule","line":32,"character":4},{"__symbolic":"reference","name":"InitiafyHeaderModule"},{"__symbolic":"reference","name":"InitiafySidenavModule"},{"__symbolic":"reference","name":"InitiafyContentModule"},{"__symbolic":"reference","name":"InitiafyActionBarModule"},{"__symbolic":"reference","name":"InitiafyActionButtonModule"},{"__symbolic":"reference","name":"InitiafyButtonModule"},{"__symbolic":"reference","name":"InitiafyCardModule"},{"__symbolic":"reference","name":"ɵi"},{"__symbolic":"reference","name":"InitiafyIconModule"},{"__symbolic":"reference","name":"InitiafyLoadingCardModule"},{"__symbolic":"reference","name":"InitiafyModalModule"},{"__symbolic":"reference","name":"InitiafyProgressBarModule"},{"__symbolic":"reference","name":"InitiafyResultModule"},{"__symbolic":"reference","name":"InitiafySearchBarModule"},{"__symbolic":"reference","name":"ɵp"},{"__symbolic":"reference","name":"InitiafySpinnerModule"},{"__symbolic":"reference","name":"ɵu"}],"exports":[{"__symbolic":"reference","name":"InitiafyHeaderModule"},{"__symbolic":"reference","name":"InitiafySidenavModule"},{"__symbolic":"reference","name":"InitiafyContentModule"},{"__symbolic":"reference","name":"InitiafyActionBarModule"},{"__symbolic":"reference","name":"InitiafyActionButtonModule"},{"__symbolic":"reference","name":"InitiafyButtonModule"},{"__symbolic":"reference","name":"InitiafyCardModule"},{"__symbolic":"reference","name":"ɵi"},{"__symbolic":"reference","name":"InitiafyIconModule"},{"__symbolic":"reference","name":"InitiafyLoadingCardModule"},{"__symbolic":"reference","name":"InitiafyModalModule"},{"__symbolic":"reference","name":"InitiafyProgressBarModule"},{"__symbolic":"reference","name":"InitiafySearchBarModule"},{"__symbolic":"reference","name":"InitiafyResultModule"},{"__symbolic":"reference","name":"InitiafySearchBarModule"},{"__symbolic":"reference","name":"ɵp"},{"__symbolic":"reference","name":"InitiafySpinnerModule"},{"__symbolic":"reference","name":"ɵu"}],"declarations":[]}]}],"members":{}},"InitiafyContentModule":{"__symbolic":"class","decorators":[{"__symbolic":"call","expression":{"__symbolic":"reference","module":"@angular/core","name":"NgModule","line":5,"character":1},"arguments":[{"imports":[{"__symbolic":"reference","module":"@angular/common","name":"CommonModule","line":6,"character":12}],"declarations":[{"__symbolic":"reference","name":"ɵc"}],"exports":[{"__symbolic":"reference","name":"ɵc"}]}]}],"members":{}},"InitiafyHeaderModule":{"__symbolic":"class","decorators":[{"__symbolic":"call","expression":{"__symbolic":"reference","module":"@angular/core","name":"NgModule","line":5,"character":1},"arguments":[{"imports":[{"__symbolic":"reference","module":"@angular/common","name":"CommonModule","line":6,"character":12}],"declarations":[{"__symbolic":"reference","name":"ɵa"}],"exports":[{"__symbolic":"reference","name":"ɵa"}]}]}],"members":{}},"InitiafySidenavModule":{"__symbolic":"class","decorators":[{"__symbolic":"call","expression":{"__symbolic":"reference","module":"@angular/core","name":"NgModule","line":5,"character":1},"arguments":[{"imports":[{"__symbolic":"reference","module":"@angular/common","name":"CommonModule","line":6,"character":12}],"declarations":[{"__symbolic":"reference","name":"ɵb"}],"exports":[{"__symbolic":"reference","name":"ɵb"}]}]}],"members":{}},"InitiafyActionBarModule":{"__symbolic":"class","decorators":[{"__symbolic":"call","expression":{"__symbolic":"reference","module":"@angular/core","name":"NgModule","line":5,"character":1},"arguments":[{"imports":[{"__symbolic":"reference","module":"@angular/common","name":"CommonModule","line":6,"character":12}],"declarations":[{"__symbolic":"reference","name":"ɵd"}],"exports":[{"__symbolic":"reference","name":"ɵd"}]}]}],"members":{}},"InitiafyActionButtonModule":{"__symbolic":"class","decorators":[{"__symbolic":"call","expression":{"__symbolic":"reference","module":"@angular/core","name":"NgModule","line":7,"character":1},"arguments":[{"imports":[{"__symbolic":"reference","module":"@angular/common","name":"CommonModule","line":9,"character":4},{"__symbolic":"reference","module":"@angular/material/tooltip","name":"MatTooltipModule","line":10,"character":4},{"__symbolic":"reference","name":"InitiafyIconModule"}],"declarations":[{"__symbolic":"reference","name":"ɵf"}],"exports":[{"__symbolic":"reference","name":"ɵf"}]}]}],"members":{}},"InitiafyButtonModule":{"__symbolic":"class","decorators":[{"__symbolic":"call","expression":{"__symbolic":"reference","module":"@angular/core","name":"NgModule","line":8,"character":1},"arguments":[{"imports":[{"__symbolic":"reference","module":"@angular/common","name":"CommonModule","line":10,"character":4},{"__symbolic":"reference","module":"@angular/material/button","name":"MatButtonModule","line":11,"character":4},{"__symbolic":"reference","module":"@angular/material/tooltip","name":"MatTooltipModule","line":12,"character":4},{"__symbolic":"reference","name":"InitiafyIconModule"}],"declarations":[{"__symbolic":"reference","name":"ɵg"}],"exports":[{"__symbolic":"reference","name":"ɵg"}]}]}],"members":{}},"InitiafyCardModule":{"__symbolic":"class","decorators":[{"__symbolic":"call","expression":{"__symbolic":"reference","module":"@angular/core","name":"NgModule","line":5,"character":1},"arguments":[{"imports":[{"__symbolic":"reference","module":"@angular/common","name":"CommonModule","line":6,"character":12}],"declarations":[{"__symbolic":"reference","name":"ɵh"}],"exports":[{"__symbolic":"reference","name":"ɵh"}]}]}],"members":{}},"InitiafyIconModule":{"__symbolic":"class","decorators":[{"__symbolic":"call","expression":{"__symbolic":"reference","module":"@angular/core","name":"NgModule","line":5,"character":1},"arguments":[{"imports":[{"__symbolic":"reference","module":"@angular/common","name":"CommonModule","line":6,"character":12},{"__symbolic":"reference","module":"@angular/material/tooltip","name":"MatTooltipModule","line":6,"character":26}],"declarations":[{"__symbolic":"reference","name":"ɵe"}],"exports":[{"__symbolic":"reference","name":"ɵe"}]}]}],"members":{}},"InitiafyLoadingCardModule":{"__symbolic":"class","decorators":[{"__symbolic":"call","expression":{"__symbolic":"reference","module":"@angular/core","name":"NgModule","line":8,"character":1},"arguments":[{"imports":[{"__symbolic":"reference","module":"@angular/common","name":"CommonModule","line":9,"character":12},{"__symbolic":"reference","name":"InitiafyCardModule"},{"__symbolic":"reference","name":"InitiafyProgressBarModule"}],"declarations":[{"__symbolic":"reference","name":"ɵl"}],"exports":[{"__symbolic":"reference","name":"ɵl"}]}]}],"members":{}},"InitiafyModalModule":{"__symbolic":"class","decorators":[{"__symbolic":"call","expression":{"__symbolic":"reference","module":"@angular/core","name":"NgModule","line":6,"character":1},"arguments":[{"imports":[{"__symbolic":"reference","module":"@angular/common","name":"CommonModule","line":7,"character":12},{"__symbolic":"reference","name":"InitiafyIconModule"}],"declarations":[{"__symbolic":"reference","name":"ɵm"}],"exports":[{"__symbolic":"reference","name":"ɵm"}]}]}],"members":{}},"InitiafyProgressBarModule":{"__symbolic":"class","decorators":[{"__symbolic":"call","expression":{"__symbolic":"reference","module":"@angular/core","name":"NgModule","line":5,"character":1},"arguments":[{"imports":[{"__symbolic":"reference","module":"@angular/common","name":"CommonModule","line":6,"character":12}],"declarations":[{"__symbolic":"reference","name":"ɵk"}],"exports":[{"__symbolic":"reference","name":"ɵk"}]}]}],"members":{}},"InitiafyResultModule":{"__symbolic":"class","decorators":[{"__symbolic":"call","expression":{"__symbolic":"reference","module":"@angular/core","name":"NgModule","line":5,"character":1},"arguments":[{"imports":[{"__symbolic":"reference","module":"@angular/common","name":"CommonModule","line":7,"character":4},{"__symbolic":"reference","name":"InitiafyIconModule"}],"declarations":[{"__symbolic":"reference","name":"ɵn"}],"exports":[{"__symbolic":"reference","name":"ɵn"}]}]}],"members":{}},"InitiafySearchBarModule":{"__symbolic":"class","decorators":[{"__symbolic":"call","expression":{"__symbolic":"reference","module":"@angular/core","name":"NgModule","line":10,"character":1},"arguments":[{"imports":[{"__symbolic":"reference","module":"@angular/common","name":"CommonModule","line":12,"character":4},{"__symbolic":"reference","module":"@angular/forms","name":"FormsModule","line":13,"character":4},{"__symbolic":"reference","module":"@angular/forms","name":"ReactiveFormsModule","line":14,"character":4},{"__symbolic":"reference","module":"@angular/material","name":"MatFormFieldModule","line":15,"character":4},{"__symbolic":"reference","module":"@angular/material/input","name":"MatInputModule","line":16,"character":4},{"__symbolic":"reference","module":"@angular/material","name":"MatButtonModule","line":17,"character":4},{"__symbolic":"reference","module":"@angular/material","name":"MatIconModule","line":18,"character":4},{"__symbolic":"reference","name":"InitiafyButtonModule"},{"__symbolic":"reference","name":"InitiafyIconModule"}],"declarations":[{"__symbolic":"reference","name":"ɵo"}],"exports":[{"__symbolic":"reference","name":"ɵo"}]}]}],"members":{}},"InitiafySpinnerModule":{"__symbolic":"class","decorators":[{"__symbolic":"call","expression":{"__symbolic":"reference","module":"@angular/core","name":"NgModule","line":5,"character":1},"arguments":[{"imports":[{"__symbolic":"reference","module":"@angular/material","name":"MatProgressSpinnerModule","line":6,"character":12}],"declarations":[{"__symbolic":"reference","name":"ɵt"}],"exports":[{"__symbolic":"reference","name":"ɵt"}]}]}],"members":{}},"ɵa":{"__symbolic":"class","decorators":[{"__symbolic":"call","expression":{"__symbolic":"reference","module":"@angular/core","name":"Component","line":2,"character":1},"arguments":[{"selector":"initiafy-header","template":"<div class=\"initiafy-header-wrapper\">\n  <div class=\"initiafy-header\">\n    <ng-content></ng-content>\n  </div>\n</div>","styles":[""]}]}],"members":{"__ctor__":[{"__symbolic":"constructor"}],"ngOnInit":[{"__symbolic":"method"}]}},"ɵb":{"__symbolic":"class","decorators":[{"__symbolic":"call","expression":{"__symbolic":"reference","module":"@angular/core","name":"Component","line":2,"character":1},"arguments":[{"selector":"initiafy-sidenav","template":"<div id=\"initiafySidenav\">\n  <div class=\"initiafy-sidenav-container\">\n    <ng-content></ng-content>\n  </div>\n</div>","styles":[""]}]}],"members":{"__ctor__":[{"__symbolic":"constructor"}],"ngOnInit":[{"__symbolic":"method"}]}},"ɵc":{"__symbolic":"class","decorators":[{"__symbolic":"call","expression":{"__symbolic":"reference","module":"@angular/core","name":"Component","line":2,"character":1},"arguments":[{"selector":"initiafy-content","template":"<div class=\"initiafy-content\">\n  <ng-content></ng-content>\n</div>","styles":[""]}]}],"members":{"__ctor__":[{"__symbolic":"constructor"}],"ngOnInit":[{"__symbolic":"method"}]}},"ɵd":{"__symbolic":"class","decorators":[{"__symbolic":"call","expression":{"__symbolic":"reference","module":"@angular/core","name":"Component","line":2,"character":1},"arguments":[{"selector":"initiafy-action-bar","template":"<div class=\"action-bar\" [ngClass]=\"cssClasses\">\n  <ng-content></ng-content>\n</div>","styles":[""]}]}],"members":{"cssClass":[{"__symbolic":"property","decorators":[{"__symbolic":"call","expression":{"__symbolic":"reference","module":"@angular/core","name":"Input","line":8,"character":3}}]}],"content":[{"__symbolic":"property","decorators":[{"__symbolic":"call","expression":{"__symbolic":"reference","module":"@angular/core","name":"Input","line":9,"character":3}}]}],"isLoading":[{"__symbolic":"property","decorators":[{"__symbolic":"call","expression":{"__symbolic":"reference","module":"@angular/core","name":"Input","line":10,"character":3}}]}],"__ctor__":[{"__symbolic":"constructor"}],"ngOnInit":[{"__symbolic":"method"}]}},"ɵe":{"__symbolic":"class","decorators":[{"__symbolic":"call","expression":{"__symbolic":"reference","module":"@angular/core","name":"Component","line":2,"character":1},"arguments":[{"selector":"initiafy-icon","template":"<i [ngClass]=\"iconClasses\" [class]=\"size\" [matTooltip]=\"tooltip\">\n  <ng-container *ngIf=\"showText\">{{ icon }}</ng-container>\n</i>","styles":[""]}]}],"members":{"icon":[{"__symbolic":"property","decorators":[{"__symbolic":"call","expression":{"__symbolic":"reference","module":"@angular/core","name":"Input","line":9,"character":3}}]}],"iconFont":[{"__symbolic":"property","decorators":[{"__symbolic":"call","expression":{"__symbolic":"reference","module":"@angular/core","name":"Input","line":10,"character":3}}]}],"size":[{"__symbolic":"property","decorators":[{"__symbolic":"call","expression":{"__symbolic":"reference","module":"@angular/core","name":"Input","line":12,"character":3}}]}],"cssClass":[{"__symbolic":"property","decorators":[{"__symbolic":"call","expression":{"__symbolic":"reference","module":"@angular/core","name":"Input","line":13,"character":3}}]}],"tooltip":[{"__symbolic":"property","decorators":[{"__symbolic":"call","expression":{"__symbolic":"reference","module":"@angular/core","name":"Input","line":14,"character":3}}]}],"__ctor__":[{"__symbolic":"constructor"}],"ngOnInit":[{"__symbolic":"method"}]}},"ɵf":{"__symbolic":"class","decorators":[{"__symbolic":"call","expression":{"__symbolic":"reference","module":"@angular/core","name":"Component","line":2,"character":1},"arguments":[{"selector":"initiafy-action-button","template":"<button \n  class=\"action-button ripple\"\n  [ngClass]=\"classes\"\n  [matTooltip]=\"tooltip\"\n  [disabled]=\"disabled\"\n  (click)=\"callback.emit($event)\">\n  <div class=\"action-button-wrapper\">\n    <ng-template [ngIf]=\"icon\">\n      <initiafy-icon [icon]=\"icon\" [iconFont]=\"iconFont\" [size]=\"size\"></initiafy-icon>\n    </ng-template>\n    <h3> {{ label }} </h3>\n  </div>\n</button>\n","styles":[""]}]}],"members":{"label":[{"__symbolic":"property","decorators":[{"__symbolic":"call","expression":{"__symbolic":"reference","module":"@angular/core","name":"Input","line":8,"character":3}}]}],"icon":[{"__symbolic":"property","decorators":[{"__symbolic":"call","expression":{"__symbolic":"reference","module":"@angular/core","name":"Input","line":9,"character":3}}]}],"iconFont":[{"__symbolic":"property","decorators":[{"__symbolic":"call","expression":{"__symbolic":"reference","module":"@angular/core","name":"Input","line":10,"character":3}}]}],"tooltip":[{"__symbolic":"property","decorators":[{"__symbolic":"call","expression":{"__symbolic":"reference","module":"@angular/core","name":"Input","line":11,"character":3}}]}],"cssClass":[{"__symbolic":"property","decorators":[{"__symbolic":"call","expression":{"__symbolic":"reference","module":"@angular/core","name":"Input","line":12,"character":3}}]}],"size":[{"__symbolic":"property","decorators":[{"__symbolic":"call","expression":{"__symbolic":"reference","module":"@angular/core","name":"Input","line":13,"character":3}}]}],"disabled":[{"__symbolic":"property","decorators":[{"__symbolic":"call","expression":{"__symbolic":"reference","module":"@angular/core","name":"Input","line":14,"character":3}}]}],"callback":[{"__symbolic":"property","decorators":[{"__symbolic":"call","expression":{"__symbolic":"reference","module":"@angular/core","name":"Output","line":15,"character":3}}]}],"__ctor__":[{"__symbolic":"constructor"}]}},"ɵg":{"__symbolic":"class","decorators":[{"__symbolic":"call","expression":{"__symbolic":"reference","module":"@angular/core","name":"Component","line":2,"character":1},"arguments":[{"selector":"initiafy-button","template":"<button \n  mat-button\n  class=\"button\"\n  [class.single]=\"!label\"\n  [ngClass]=\"classes\"\n  [type]=\"type\"\n  [matTooltip]=\"tooltip\"\n  [disabled]=\"disabled\"\n  (click)=\"callback.emit($event)\"\n  >\n  <ng-template [ngIf]=\"icon\"><initiafy-icon [icon]=\"icon\" [iconFont]=\"iconFont\"></initiafy-icon></ng-template>\n  <ng-template [ngIf]=\"label\"><span class=\"button-label\">{{ label }}</span></ng-template>\n</button>\n","styles":[""]}]}],"members":{"design":[{"__symbolic":"property","decorators":[{"__symbolic":"call","expression":{"__symbolic":"reference","module":"@angular/core","name":"Input","line":9,"character":3}}]}],"color":[{"__symbolic":"property","decorators":[{"__symbolic":"call","expression":{"__symbolic":"reference","module":"@angular/core","name":"Input","line":11,"character":3}}]}],"label":[{"__symbolic":"property","decorators":[{"__symbolic":"call","expression":{"__symbolic":"reference","module":"@angular/core","name":"Input","line":13,"character":3}}]}],"type":[{"__symbolic":"property","decorators":[{"__symbolic":"call","expression":{"__symbolic":"reference","module":"@angular/core","name":"Input","line":15,"character":3}}]}],"icon":[{"__symbolic":"property","decorators":[{"__symbolic":"call","expression":{"__symbolic":"reference","module":"@angular/core","name":"Input","line":17,"character":3}}]}],"iconFont":[{"__symbolic":"property","decorators":[{"__symbolic":"call","expression":{"__symbolic":"reference","module":"@angular/core","name":"Input","line":19,"character":3}}]}],"cssClass":[{"__symbolic":"property","decorators":[{"__symbolic":"call","expression":{"__symbolic":"reference","module":"@angular/core","name":"Input","line":22,"character":3}}]}],"tooltip":[{"__symbolic":"property","decorators":[{"__symbolic":"call","expression":{"__symbolic":"reference","module":"@angular/core","name":"Input","line":24,"character":3}}]}],"disabled":[{"__symbolic":"property","decorators":[{"__symbolic":"call","expression":{"__symbolic":"reference","module":"@angular/core","name":"Input","line":26,"character":3}}]}],"hideLabelOnMobile":[{"__symbolic":"property","decorators":[{"__symbolic":"call","expression":{"__symbolic":"reference","module":"@angular/core","name":"Input","line":28,"character":3}}]}],"callback":[{"__symbolic":"property","decorators":[{"__symbolic":"call","expression":{"__symbolic":"reference","module":"@angular/core","name":"Output","line":30,"character":3}}]}],"__ctor__":[{"__symbolic":"constructor"}],"ngOnInit":[{"__symbolic":"method"}]}},"ɵh":{"__symbolic":"class","decorators":[{"__symbolic":"call","expression":{"__symbolic":"reference","module":"@angular/core","name":"Component","line":2,"character":1},"arguments":[{"selector":"initiafy-card","template":"<div class=\"initiafy-card\" [ngClass]=\"cssClass\">\n  <ng-content></ng-content>\n</div>","styles":[""]}]}],"members":{"cssClass":[{"__symbolic":"property","decorators":[{"__symbolic":"call","expression":{"__symbolic":"reference","module":"@angular/core","name":"Input","line":8,"character":3}}]}],"__ctor__":[{"__symbolic":"constructor"}]}},"ɵi":{"__symbolic":"class","decorators":[{"__symbolic":"call","expression":{"__symbolic":"reference","module":"@angular/core","name":"NgModule","line":14,"character":1},"arguments":[{"declarations":[{"__symbolic":"reference","name":"ɵj"}],"imports":[{"__symbolic":"reference","module":"@angular/common","name":"CommonModule","line":17,"character":4},{"__symbolic":"reference","name":"InitiafyButtonModule"},{"__symbolic":"reference","module":"@angular/material","name":"MatIconModule","line":19,"character":4},{"__symbolic":"reference","module":"@angular/material","name":"MatCheckboxModule","line":20,"character":4},{"__symbolic":"reference","module":"@angular/material","name":"MatMenuModule","line":21,"character":4},{"__symbolic":"reference","module":"@angular/material","name":"MatFormFieldModule","line":22,"character":4},{"__symbolic":"reference","module":"@angular/material","name":"MatPaginatorModule","line":23,"character":4},{"__symbolic":"reference","module":"@angular/material","name":"MatTableModule","line":24,"character":4},{"__symbolic":"reference","module":"@angular/material","name":"MatInputModule","line":25,"character":4}],"exports":[{"__symbolic":"reference","name":"ɵj"}]}]}],"members":{}},"ɵj":{"__symbolic":"class","arity":1,"decorators":[{"__symbolic":"call","expression":{"__symbolic":"reference","module":"@angular/core","name":"Component","line":16,"character":1},"arguments":[{"selector":"initiafy-data-table","template":"<mat-table [dataSource]=\"dataTableSettings.dataSource\">\n  <ng-container matColumnDef=\"checkbox\">\n    <mat-header-cell *matHeaderCellDef mat-sort-header [ngClass]=\"'customCheckboxColumnClass'\">\n      <mat-checkbox [checked]=\"isAllSelected\" [indeterminate]=\"areSomeSelected\" (change)=\"masterCheckboxChange($event)\">\n      </mat-checkbox>\n    </mat-header-cell>\n    <mat-cell *matCellDef=\"let row\" [ngClass]=\"'customCheckboxColumnClass'\">\n      <mat-checkbox [checked]=\"isItemSelected(row)\" class=\"the_checkboxes\" (change)=\"checkboxChange($event, row)\">\n      </mat-checkbox>\n      <initiafy-button class=\"show_in_small_screen align-right-small-screen\" *ngIf=\"dataTableSettings.menu\"\n        [matMenuTriggerFor]=\"appMenu\" (click)=\"clickedItem = row\" icon=\"more_vert\" [disabled]=\"!dataTableSettings.menu\">\n      </initiafy-button>\n    </mat-cell>\n  </ng-container>\n  <ng-container matColumnDef=\"menu\">\n    <mat-header-cell *matHeaderCellDef mat-sort-header [ngClass]=\"'customMenuColumnClass flex justify-content-center'\">\n    </mat-header-cell>\n    <mat-cell class=\"hide_in_small_screen\" *matCellDef=\"let row\"\n      [ngClass]=\"'customMenuColumnClass flex justify-content-center'\">\n      <initiafy-button [matMenuTriggerFor]=\"appMenu\" (click)=\"clickedItem = row\" [cssClass]=\"'row-action-button'\"\n        icon=\"more_vert\" [disabled]=\"!dataTableSettings.menu\">\n      </initiafy-button>\n    </mat-cell>\n  </ng-container>\n  <ng-container *ngFor=\"let column of dataTableSettings.columnDefinitions; trackBy: trackByColumnName\"\n    [matColumnDef]=\"column.columnName\">\n    <mat-header-cell *matHeaderCellDef mat-sort-header\n      [class.customExtraCheckboxColumnClass]=\"column.mode === 'extra-checkbox'\"\n      [ngClass]=\"smallcreen ? column.customHeaderClassSm : column.customHeaderClassLg\">\n      {{ column.title }}\n    </mat-header-cell>\n    <ng-container [ngSwitch]=\"column.mode\">\n      <ng-container *ngSwitchCase=\"'nested'\">\n        <mat-cell *matCellDef=\"let row\" class=\"block_small_screen\" [attr.data-label]=\"column.title\"\n          [ngClass]=\"smallcreen ? column.customCellClassSm : column.customCellClassLg\"\n          (click)=\"handleCellClick(column, row)\" [class.pointer]=\"column.handleCellClick\">\n          {{ getNestedValue(column, row) }}\n        </mat-cell>\n      </ng-container>\n      <ng-container *ngSwitchCase=\"'count'\">\n        <mat-cell *matCellDef=\"let row\" class=\"block_small_screen\" [attr.data-label]=\"column.title\"\n          [ngClass]=\"smallcreen ? column.customCellClassSm : column.customCellClassLg\"\n          (click)=\"handleCellClick(column, row)\" [class.pointer]=\"column.handleCellClick\">\n          {{ row.cnt }}\n        </mat-cell>\n      </ng-container>\n      <ng-container *ngSwitchCase=\"'transformer'\">\n        <mat-cell *matCellDef=\"let row\" class=\"block_small_screen\" [attr.data-label]=\"column.title\"\n          [ngClass]=\"smallcreen ? column.customCellClassSm : column.customCellClassLg\"\n          (click)=\"handleCellClick(column, row)\" [class.pointer]=\"column.handleCellClick\">\n          {{ column.transformer(row) }}\n        </mat-cell>\n      </ng-container>\n      <ng-container *ngSwitchCase=\"'extra-checkbox'\">\n        <mat-cell *matCellDef=\"let row\" class=\"block_small_screen customExtraCheckboxColumnClass\"\n          [attr.data-label]=\"column.title\" [ngClass]=\"smallcreen ? column.customCellClassSm : column.customCellClassLg\"\n          (click)=\"handleCellClick(column, row)\" [class.pointer]=\"column.handleCellClick\">\n          <mat-checkbox [disabled]=\"column.disableFormField(row)\"\n            [checked]=\"column.checkboxSettings.checkboxChecked(row)\"\n            (change)=\"column.checkboxSettings.checkboxChange($event, row)\" class=\"margin-x-auto\"></mat-checkbox>\n        </mat-cell>\n      </ng-container>\n      <ng-container *ngSwitchCase=\"'list'\">\n        <mat-cell *matCellDef=\"let row\" class=\"block_small_screen\"\n          [attr.data-label]=\"column.title\" [ngClass]=\"smallcreen ? column.customCellClassSm : column.customCellClassLg\"\n          [class.pointer]=\"column.handleCellClick\">\n          <ul>\n            <li *ngFor=\"let item of column.listAccessor(row)\">{{item}}</li>\n          </ul>\n        </mat-cell>\n      </ng-container>\n      <ng-container *ngSwitchCase=\"'input'\">\n        <mat-cell *matCellDef=\"let row\" [attr.data-label]=\"column.title\" class=\"block_small_screen input-cell\"\n          [ngClass]=\"smallcreen ? column.customCellClassSm : column.customCellClassLg\"\n          (click)=\"handleCellClick(column, row)\" [class.pointer]=\"column.handleCellClick\">\n          <mat-form-field class=\"column-input-form-field\" floatLabel=\"always\">\n            <input [disabled]=\"column.disableFormField(row)\" [placeholder]=\"smallcreen ? column.title : ''\" matInput\n              (keyup)=\"column.inputSettings.inputChange($event, row)\" [value]=\"column.inputSettings.inputValue(row)\" />\n          </mat-form-field>\n        </mat-cell>\n      </ng-container>\n      <ng-container *ngSwitchDefault>\n        <mat-cell *matCellDef=\"let row\" class=\"block_small_screen\"\n          [ngClass]=\"smallcreen ? column.customCellClassSm : column.customCellClassLg\" [attr.data-label]=\"column.title\"\n          (click)=\"handleCellClick(column, row)\" [class.pointer]=\"column.handleCellClick\">\n          {{ row[column.columnName] }}\n        </mat-cell>\n      </ng-container>\n    </ng-container>\n  </ng-container>\n  <mat-header-row *matHeaderRowDef=\"dataTableSettings.displayedColumns\"></mat-header-row>\n  <mat-row *matRowDef=\"let row; columns: dataTableSettings.displayedColumns\"\n    [class.hover-bgcolor]=\"!dataTableSettings.hideSelectedRowHighlighting && isRowSelected(row)\"\n    [class.pointer]=\"!!dataTableSettings.clickableRows\" (click)=\"handleRowClick($event, row)\"></mat-row>\n</mat-table>\n\n<mat-paginator [pageSizeOptions]=\"[5, 10, 25, 100]\"></mat-paginator>\n\n<mat-menu #appMenu=\"matMenu\">\n  <div *ngIf=\"dataTableSettings.menu\">\n    <ng-container *ngFor=\"let item of dataTableSettings.menu\">\n      <button mat-menu-item (click)=\"item.action(clickedItem)\" [disabled]=\"item.disabled && item.disabled(clickedItem)\">\n        <mat-icon>{{ item.icon }}</mat-icon>\n        {{ item.label }}\n      </button>\n    </ng-container>\n  </div>\n</mat-menu>","styles":[".customCheckboxColumnClass{flex:0 1 58px}.customExtraCheckboxColumnClass,.customMenuColumnClass{flex:0 1 80px;justify-content:center}.show_in_small_screen{display:none}.column-input-form-field{width:100%}@media screen and (max-width:960px){.block_small_screen{display:block}.the_checkboxes{margin-bottom:8px;margin-left:8px}.mat-table{border:0;vertical-align:middle}.align-right-small-screen{margin-left:auto}.mat-table caption{font-size:1em}mat-cell:first-of-type,mat-footer-cell:first-of-type,mat-header-cell:first-of-type{padding-left:0}mat-cell:last-of-type,mat-footer-cell:last-of-type,mat-header-cell:last-of-type{padding-right:0}mat-footer-row::after,mat-header-row::after,mat-row::after{min-height:auto}.mat-table .mat-header-cell{border:10px solid;clip:rect(0 0 0 0);height:1px;margin:-1px;padding:0;position:absolute;width:1px}.mat-header-row{display:none}.mat-table .mat-row{border-bottom:5px solid #ddd;display:block}.mat-table .mat-cell{border-bottom:1px solid #ddd;font-size:1em;text-align:right;height:30px;margin-bottom:4%;padding-left:8px;padding-right:8px}.mat-table .mat-cell:not(.input-cell):before{content:attr(data-label);float:left;color:rgba(0,0,0,.54);font-weight:400;font-size:12px}.mat-table .mat-cell:last-child{border-bottom:0}.mat-table .mat-cell:first-child{margin-top:4%}.hide_in_small_screen{display:none}.show_in_small_screen{display:block}}ul{list-style:none;padding-left:0}"]}]}],"members":{"dataTableSettings":[{"__symbolic":"property","decorators":[{"__symbolic":"call","expression":{"__symbolic":"reference","module":"@angular/core","name":"Input","line":24,"character":3}}]}],"selectionModel":[{"__symbolic":"property","decorators":[{"__symbolic":"call","expression":{"__symbolic":"reference","module":"@angular/core","name":"Input","line":27,"character":3}}]}],"selectionModelChange":[{"__symbolic":"property","decorators":[{"__symbolic":"call","expression":{"__symbolic":"reference","module":"@angular/core","name":"Output","line":31,"character":3}}]}],"paginator":[{"__symbolic":"property","decorators":[{"__symbolic":"call","expression":{"__symbolic":"reference","module":"@angular/core","name":"ViewChild","line":37,"character":3},"arguments":[{"__symbolic":"reference","module":"@angular/material","name":"MatPaginator","line":37,"character":13}]}]}],"sort":[{"__symbolic":"property","decorators":[{"__symbolic":"call","expression":{"__symbolic":"reference","module":"@angular/core","name":"ViewChild","line":38,"character":3},"arguments":[{"__symbolic":"reference","module":"@angular/material","name":"MatSort","line":38,"character":13}]}]}],"checkboxes":[{"__symbolic":"property","decorators":[{"__symbolic":"call","expression":{"__symbolic":"reference","module":"@angular/core","name":"ViewChildren","line":39,"character":3},"arguments":[{"__symbolic":"reference","module":"@angular/material","name":"MatCheckbox","line":39,"character":16}]}]}],"__ctor__":[{"__symbolic":"constructor"}],"ngAfterViewInit":[{"__symbolic":"method"}],"ngOnInit":[{"__symbolic":"method"}],"checkboxChange":[{"__symbolic":"method"}],"isItemSelected":[{"__symbolic":"method"}],"masterCheckboxChange":[{"__symbolic":"method"}],"trackByColumnName":[{"__symbolic":"method"}],"handleRowClick":[{"__symbolic":"method"}],"handleCellClick":[{"__symbolic":"method"}],"getNestedValue":[{"__symbolic":"method"}],"isRowSelected":[{"__symbolic":"method"}]}},"ɵk":{"__symbolic":"class","decorators":[{"__symbolic":"call","expression":{"__symbolic":"reference","module":"@angular/core","name":"Component","line":2,"character":1},"arguments":[{"selector":"initiafy-progress-bar","template":"<div class=\"progress-bar\" *ngIf=\"isLoading\">\n    <div class=\"indeterminate\"></div>\n</div>","styles":[""]}]}],"members":{"isLoading":[{"__symbolic":"property","decorators":[{"__symbolic":"call","expression":{"__symbolic":"reference","module":"@angular/core","name":"Input","line":8,"character":3}}]}],"__ctor__":[{"__symbolic":"constructor"}],"ngOnInit":[{"__symbolic":"method"}]}},"ɵl":{"__symbolic":"class","decorators":[{"__symbolic":"call","expression":{"__symbolic":"reference","module":"@angular/core","name":"Component","line":2,"character":1},"arguments":[{"selector":"initiafy-loading-card","template":"<div class=\"loading-card\" [ngClass]=\"classes\">\n  <div class=\"loading-card-content\">\n    <ng-content></ng-content>\n  </div>\n  <initiafy-progress-bar [isLoading]=\"isLoading\" class=\"loading-card-bar\"></initiafy-progress-bar>\n</div>","styles":[":host{width:100%;display:flex;align-items:center;justify-content:center}"]}]}],"members":{"cssClass":[{"__symbolic":"property","decorators":[{"__symbolic":"call","expression":{"__symbolic":"reference","module":"@angular/core","name":"Input","line":8,"character":3}}]}],"size":[{"__symbolic":"property","decorators":[{"__symbolic":"call","expression":{"__symbolic":"reference","module":"@angular/core","name":"Input","line":9,"character":3}}]}],"isLoading":[{"__symbolic":"property","decorators":[{"__symbolic":"call","expression":{"__symbolic":"reference","module":"@angular/core","name":"Input","line":10,"character":3}}]}],"__ctor__":[{"__symbolic":"constructor"}],"ngOnInit":[{"__symbolic":"method"}]}},"ɵm":{"__symbolic":"class","decorators":[{"__symbolic":"call","expression":{"__symbolic":"reference","module":"@angular/core","name":"Component","line":2,"character":1},"arguments":[{"selector":"initiafy-modal","template":"<div class=\"initiafy-modal\" [class.is-overlay]=\"overlay\">\n  <div class=\"initiafy-modal-root\">\n    <div class=\"initiafy-modal-close\" (click)=\"close.emit()\" *ngIf=\"!hideCloseButton\">\n      <initiafy-icon icon=\"close\"></initiafy-icon>\n    </div>\n    <div class=\"initiafy-modal-content\">\n      <div class=\"flex justify-content-center column full-height\">\n        <ng-content></ng-content>\n      </div>\n    </div>\n  </div>\n</div>","styles":[""]}]}],"members":{"overlay":[{"__symbolic":"property","decorators":[{"__symbolic":"call","expression":{"__symbolic":"reference","module":"@angular/core","name":"Input","line":8,"character":3}}]}],"hideCloseButton":[{"__symbolic":"property","decorators":[{"__symbolic":"call","expression":{"__symbolic":"reference","module":"@angular/core","name":"Input","line":9,"character":3}}]}],"close":[{"__symbolic":"property","decorators":[{"__symbolic":"call","expression":{"__symbolic":"reference","module":"@angular/core","name":"Output","line":10,"character":3}}]}],"__ctor__":[{"__symbolic":"constructor"}],"ngOnInit":[{"__symbolic":"method"}]}},"ɵn":{"__symbolic":"class","decorators":[{"__symbolic":"call","expression":{"__symbolic":"reference","module":"@angular/core","name":"Component","line":2,"character":1},"arguments":[{"selector":"initiafy-result","template":"<ng-template [ngIf]=\"hasData\" [ngIfElse]=\"emptyContainer\">\n  <ng-content></ng-content>\n</ng-template>\n<ng-template #emptyContainer>\n  <div class=\"full-width flex-justify-align-center column default height-500\">\n    <initiafy-icon cssClass=\"feedback-color\" icon=\"{{ icon }}\" iconFont=\"{{ iconFont }}\" size=\"big\"></initiafy-icon>\n    <p class=\"text24 feedback-color text-center margin-y-std\">{{ message }}</p>\n  </div>\n</ng-template>\n","styles":[""]}]}],"members":{"icon":[{"__symbolic":"property","decorators":[{"__symbolic":"call","expression":{"__symbolic":"reference","module":"@angular/core","name":"Input","line":8,"character":3}}]}],"iconFont":[{"__symbolic":"property","decorators":[{"__symbolic":"call","expression":{"__symbolic":"reference","module":"@angular/core","name":"Input","line":9,"character":3}}]}],"message":[{"__symbolic":"property","decorators":[{"__symbolic":"call","expression":{"__symbolic":"reference","module":"@angular/core","name":"Input","line":10,"character":3}}]}],"hasData":[{"__symbolic":"property","decorators":[{"__symbolic":"call","expression":{"__symbolic":"reference","module":"@angular/core","name":"Input","line":11,"character":3}}]}],"__ctor__":[{"__symbolic":"constructor"}],"ngOnInit":[{"__symbolic":"method"}]}},"ɵo":{"__symbolic":"class","decorators":[{"__symbolic":"call","expression":{"__symbolic":"reference","module":"@angular/core","name":"Component","line":8,"character":1},"arguments":[{"selector":"initiafy-search-bar","template":"<form (ngSubmit)=\"onSubmit()\">\n  <div class=\"flex align-items-flex-end\">\n    <ng-template\n      #notCollapsedTemplate\n      [ngIf]=\"!collapsed\"\n      [ngIfElse]=\"collapsedTemplate\"\n    >\n      <mat-form-field\n        [color]=\"color\"\n        floatLabel=\"always\"\n        class=\"example-form-field\"\n      >\n        <input\n          matInput\n          type=\"text\"\n          [placeholder]=\"placeholder\"\n          [(ngModel)]=\"value\"\n          name=\"value\"\n        />\n        <button\n          mat-button\n          *ngIf=\"value\"\n          type=\"button\"\n          matSuffix\n          mat-icon-button\n          aria-label=\"Clear\"\n          (click)=\"value = ''\"\n        >\n          <mat-icon>close</mat-icon>\n        </button>\n      </mat-form-field>\n      <initiafy-button\n        class=\"margin-bottom-20 flex align-items-end\"\n        [label]=\"buttontext\"\n        [color]=\"color\"\n        type=\"submit\"\n        aria-label=\"Search\"\n      >\n      </initiafy-button>\n    </ng-template>\n    <ng-template #collapsedTemplate>\n      <initiafy-button\n        class=\"margin-bottom-20 flex align-items-end\"\n        type=\"button\"\n        (callback)=\"unCollapse()\"\n        [icon]=\"buttonicon\"\n        [color]=\"color\"\n        aria-label=\"Search\"\n      >\n      </initiafy-button>\n    </ng-template>\n  </div>\n</form>\n","styles":[":host{display:block}"]}]}],"members":{"placeholder":[{"__symbolic":"property","decorators":[{"__symbolic":"call","expression":{"__symbolic":"reference","module":"@angular/core","name":"Input","line":15,"character":3}}]}],"color":[{"__symbolic":"property","decorators":[{"__symbolic":"call","expression":{"__symbolic":"reference","module":"@angular/core","name":"Input","line":17,"character":3}}]}],"value":[{"__symbolic":"property","decorators":[{"__symbolic":"call","expression":{"__symbolic":"reference","module":"@angular/core","name":"Input","line":19,"character":3}}]}],"buttontext":[{"__symbolic":"property","decorators":[{"__symbolic":"call","expression":{"__symbolic":"reference","module":"@angular/core","name":"Input","line":21,"character":3}}]}],"buttonicon":[{"__symbolic":"property","decorators":[{"__symbolic":"call","expression":{"__symbolic":"reference","module":"@angular/core","name":"Input","line":23,"character":3}}]}],"search":[{"__symbolic":"property","decorators":[{"__symbolic":"call","expression":{"__symbolic":"reference","module":"@angular/core","name":"Output","line":25,"character":3}}]}],"collapsed":[{"__symbolic":"property","decorators":[{"__symbolic":"call","expression":{"__symbolic":"reference","module":"@angular/core","name":"Input","line":30,"character":3}}]}],"collapsedChange":[{"__symbolic":"property","decorators":[{"__symbolic":"call","expression":{"__symbolic":"reference","module":"@angular/core","name":"Output","line":34,"character":3}}]}],"__ctor__":[{"__symbolic":"constructor"}],"ngOnInit":[{"__symbolic":"method"}],"onSubmit":[{"__symbolic":"method"}],"unCollapse":[{"__symbolic":"method"}]}},"ɵp":{"__symbolic":"class","decorators":[{"__symbolic":"call","expression":{"__symbolic":"reference","module":"@angular/core","name":"NgModule","line":8,"character":1},"arguments":[{"declarations":[{"__symbolic":"reference","name":"ɵq"}],"imports":[{"__symbolic":"reference","module":"@angular/common","name":"CommonModule","line":11,"character":4},{"__symbolic":"reference","module":"@angular/material","name":"MatSnackBarModule","line":12,"character":4},{"__symbolic":"reference","name":"InitiafyIconModule"},{"__symbolic":"reference","name":"InitiafyButtonModule"}],"providers":[{"__symbolic":"reference","name":"ɵs"}],"entryComponents":[{"__symbolic":"reference","name":"ɵq"}]}]}],"members":{}},"ɵq":{"__symbolic":"class","decorators":[{"__symbolic":"call","expression":{"__symbolic":"reference","module":"@angular/core","name":"Component","line":4,"character":1},"arguments":[{"selector":"initiafy-snack-bar","template":"<div class=\"full-width flex row align-items-center justify-content-space-between white-color mat-simple-snackbar\">\n  <div class=\"flex align-items-center default\">\n    <initiafy-icon *ngIf=\"data.icon\" class=\"margin-right-8\" [icon]=\"data.icon\"\n      [iconFont]=\"data.iconFont ?  data.iconFont : 'material-outlined'\"></initiafy-icon>\n    {{ data.message }}\n  </div>\n  <initiafy-button design=\"basic\" [cssClass]=\"'white-color'\" *ngIf=\"data.actionButtonLabel\" [label]=\"data.actionButtonLabel\" [tooltip]=\"data.actionButtonLabel\"\n    [disabled]=\"false\"></initiafy-button>\n  <initiafy-icon *ngIf=\"data.closeButton\" class=\"margin-left-16 noselect pointer\" (click)=\"dismiss()\"\n    [icon]=\"'close'\" [iconFont]=\"data.iconFont ?  data.iconFont : 'material-outlined'\"></initiafy-icon>\n  <!-- <mat-icon class=\"margin-left-16 noselect pointer\" *ngIf=\"data.closeButton\" (click)=\"dismiss()\">close</mat-icon> -->\n</div>","styles":[""]}]}],"members":{"__ctor__":[{"__symbolic":"constructor","parameterDecorators":[[{"__symbolic":"call","expression":{"__symbolic":"reference","module":"@angular/core","name":"Inject","line":12,"character":5},"arguments":[{"__symbolic":"reference","module":"@angular/material","name":"MAT_SNACK_BAR_DATA","line":12,"character":12}]}],null],"parameters":[{"__symbolic":"reference","name":"ɵr"},{"__symbolic":"reference","module":"@angular/material","name":"MatSnackBar","line":13,"character":22}]}],"ngOnInit":[{"__symbolic":"method"}],"dismiss":[{"__symbolic":"method"}],"action":[{"__symbolic":"method"}]}},"ɵr":{"__symbolic":"interface"},"ɵs":{"__symbolic":"class","decorators":[{"__symbolic":"call","expression":{"__symbolic":"reference","module":"@angular/core","name":"Injectable","line":5,"character":1},"arguments":[{"providedIn":"root"}]}],"members":{"__ctor__":[{"__symbolic":"constructor","parameters":[{"__symbolic":"reference","module":"@angular/router","name":"Router","line":10,"character":30},{"__symbolic":"reference","module":"@angular/material","name":"MatSnackBar","line":10,"character":56}]}],"help":[{"__symbolic":"method"}],"success":[{"__symbolic":"method"}],"handleServerErrors":[{"__symbolic":"method"}],"error":[{"__symbolic":"method"}],"dismissPersistentMessages":[{"__symbolic":"method"}]},"statics":{"ngInjectableDef":{}}},"ɵt":{"__symbolic":"class","decorators":[{"__symbolic":"call","expression":{"__symbolic":"reference","module":"@angular/core","name":"Component","line":2,"character":1},"arguments":[{"selector":"initiafy-spinner","template":"<mat-spinner></mat-spinner>","styles":[""]}]}],"members":{"__ctor__":[{"__symbolic":"constructor"}],"ngOnInit":[{"__symbolic":"method"}]}},"ɵu":{"__symbolic":"class","decorators":[{"__symbolic":"call","expression":{"__symbolic":"reference","module":"@angular/core","name":"NgModule","line":7,"character":1},"arguments":[{"declarations":[{"__symbolic":"reference","name":"ɵv"}],"imports":[{"__symbolic":"reference","module":"@angular/common","name":"CommonModule","line":12,"character":4},{"__symbolic":"reference","name":"InitiafyIconModule"},{"__symbolic":"reference","module":"@angular/material","name":"MatButtonModule","line":14,"character":4},{"__symbolic":"reference","module":"@angular/material","name":"MatDialogModule","line":15,"character":4}],"exports":[{"__symbolic":"reference","name":"ɵv"}],"providers":[{"__symbolic":"reference","name":"ɵx"}],"entryComponents":[{"__symbolic":"reference","name":"ɵv"}]}]}],"members":{}},"ɵv":{"__symbolic":"class","decorators":[{"__symbolic":"call","expression":{"__symbolic":"reference","module":"@angular/core","name":"Component","line":4,"character":1},"arguments":[{"selector":"initiafy-yes-or-no","template":"<div>\n  <div class=\"flex row justify-content-end\">\n    <div class=\"pointer\" (click)=\"closeDialog()\">\n      <initiafy-icon icon=\"close\"></initiafy-icon>\n    </div>\n  </div>\n  <div class=\"flex justify-content-center\">\n    <h1 mat-dialog-title *ngIf=\"data.title\">{{ data.title }}</h1>\n  </div>\n\n  <div mat-dialog-content align=\"center\">\n    <div class=\"full-width margin-top-std\">\n      <div>\n        <initiafy-icon icon=\"warning\"></initiafy-icon>\n        <!-- <mat-icon class=\"text32\">warning</mat-icon> -->\n      </div>\n    </div>\n\n    <div class=\"full-width\">\n      <div [innerHTML]=\"data.message\">\n      </div>\n    </div>\n  </div>\n  <div class=\"full-width flex row justify-content-space-between margin-top-std\">\n    <button mat-stroked-button color=\"primary\" type=\"button\" [mat-dialog-close]=\"false\" *ngIf=\"data.noButtonLabel\">\n      {{ data.noButtonLabel }}\n    </button>\n    <button mat-flat-button color=\"primary\" type=\"button\" [mat-dialog-close]=\"true\" cdkFocusInitial>\n      {{ data.yesButtonLabel }}\n    </button>\n  </div>\n</div>","styles":[".close-icon{top:16px;right:16px;z-index:999;padding:10px}"]}]}],"members":{"__ctor__":[{"__symbolic":"constructor","parameterDecorators":[null,[{"__symbolic":"call","expression":{"__symbolic":"reference","module":"@angular/core","name":"Inject","line":12,"character":7},"arguments":[{"__symbolic":"reference","module":"@angular/material","name":"MAT_DIALOG_DATA","line":12,"character":14}]}]],"parameters":[{"__symbolic":"reference","name":"MatDialogRef","module":"@angular/material","arguments":[{"__symbolic":"reference","name":"ɵv"}]},{"__symbolic":"reference","name":"ɵw"}]}],"ngOnInit":[{"__symbolic":"method"}],"closeDialog":[{"__symbolic":"method"}]}},"ɵw":{"__symbolic":"interface"},"ɵx":{"__symbolic":"class","decorators":[{"__symbolic":"call","expression":{"__symbolic":"reference","module":"@angular/core","name":"Injectable","line":5,"character":1},"arguments":[{"providedIn":"root"}]}],"members":{"__ctor__":[{"__symbolic":"constructor","parameters":[{"__symbolic":"reference","module":"@angular/material","name":"MatDialog","line":10,"character":29}]}],"show":[{"__symbolic":"method"}]},"statics":{"ngInjectableDef":{}}}},"origins":{"DesignSystemInitiafyModule":"./design-system-initiafy.module","InitiafyContentModule":"./lib/core-components/content/content.module","InitiafyHeaderModule":"./lib/core-components/header/header.module","InitiafySidenavModule":"./lib/core-components/sidenav/sidenav.module","InitiafyActionBarModule":"./lib/action-bar/action-bar.module","InitiafyActionButtonModule":"./lib/action-button/action-button.module","InitiafyButtonModule":"./lib/button/button.module","InitiafyCardModule":"./lib/card/card.module","InitiafyIconModule":"./lib/icon/icon.module","InitiafyLoadingCardModule":"./lib/loading-card/loading-card.module","InitiafyModalModule":"./lib/modal/modal.module","InitiafyProgressBarModule":"./lib/progress-bar/progress-bar.module","InitiafyResultModule":"./lib/result/result.module","InitiafySearchBarModule":"./lib/search-bar/search-bar.module","InitiafySpinnerModule":"./lib/spinner/spinner.module","ɵa":"./lib/core-components/header/header.component","ɵb":"./lib/core-components/sidenav/sidenav.component","ɵc":"./lib/core-components/content/content.component","ɵd":"./lib/action-bar/action-bar.component","ɵe":"./lib/icon/icon.component","ɵf":"./lib/action-button/action-button.component","ɵg":"./lib/button/button.component","ɵh":"./lib/card/card.component","ɵi":"./lib/data-table/data-table.module","ɵj":"./lib/data-table/data-table/data-table.component","ɵk":"./lib/progress-bar/progress-bar.component","ɵl":"./lib/loading-card/loading-card.component","ɵm":"./lib/modal/modal.component","ɵn":"./lib/result/result.component","ɵo":"./lib/search-bar/search-bar.component","ɵp":"./lib/snack-bar/snack-bar.module","ɵq":"./lib/snack-bar/snack-bar/snack-bar.component","ɵr":"./lib/snack-bar/models/snack-bar-data","ɵs":"./lib/snack-bar/snack-bar.service","ɵt":"./lib/spinner/spinner.component","ɵu":"./lib/yes-or-no/yes-or-no.module","ɵv":"./lib/yes-or-no/yes-or-no/yes-or-no.component","ɵw":"./lib/yes-or-no/models/dialogData","ɵx":"./lib/yes-or-no/yes-or-no.service"},"importAs":"design-system-initiafy"}